solima_hello/__init__.py
solima_hello/hello.py
solima_hello-0.0.8.dist-info/DESCRIPTION.rst
solima_hello-0.0.8.dist-info/METADATA
solima_hello-0.0.8.dist-info/RECORD
solima_hello-0.0.8.dist-info/WHEEL
solima_hello-0.0.8.dist-info/entry_points.txt
solima_hello-0.0.8.dist-info/metadata.json
solima_hello-0.0.8.dist-info/top_level.txt
