Metadata-Version: 2.0
Name: solima-hello
Version: 0.0.8
Summary: solima hello world
Home-page: UNKNOWN
Author: solima
Author-email: UNKNOWN
License: GPL
Keywords: solima,hello,world
Platform: UNKNOWN
